phidl/__init__.py
phidl/device_layout.py
phidl/geometry.py
phidl/phidl_tutorial_example.py
phidl/quickplotter.py
phidl/routing.py
phidl/utilities.py
phidl-1.0.1.dist-info/DESCRIPTION.rst
phidl-1.0.1.dist-info/METADATA
phidl-1.0.1.dist-info/RECORD
phidl-1.0.1.dist-info/WHEEL
phidl-1.0.1.dist-info/metadata.json
phidl-1.0.1.dist-info/top_level.txt
