Metadata-Version: 2.0
Name: phidl
Version: 1.0.1
Summary: PHIDL
Home-page: UNKNOWN
Author: Adam McCaughan
Author-email: amccaugh@gmail.com
License: UNKNOWN
Platform: UNKNOWN
Requires-Dist: gdspy (>=1.3.1)
Requires-Dist: matplotlib
Requires-Dist: numpy
Requires-Dist: scipy
Requires-Dist: webcolors
